{"cameraMode":{"drawMode":0,"name":"Shaded","section":"Shading Mode"},"sceneLighting":true,"audioPlay":false,"sceneViewState":{"m_AlwaysRefresh":false,"showFog":true,"showSkybox":true,"showFlares":true,"showImageEffects":true,"showParticleSystems":true,"showVisualEffectGraphs":true,"m_FxEnabled":true},"in2DMode":false,"pivot":{"x":-13.743975639343262,"y":7.92613410949707,"z":5.907548904418945},"rotation":{"x":-0.012098838575184346,"y":0.7189886569976807,"z":-0.012517292983829975,"w":-0.6948111057281494},"size":35.503822326660159,"orthographic":false}